LICENSE
MANIFEST.in
README.rst
buildout.cfg
requirements.txt
setup.py
version.txt
bob/__init__.py
bob.db.swan.egg-info/PKG-INFO
bob.db.swan.egg-info/SOURCES.txt
bob.db.swan.egg-info/dependency_links.txt
bob.db.swan.egg-info/entry_points.txt
bob.db.swan.egg-info/requires.txt
bob.db.swan.egg-info/top_level.txt
bob/db/__init__.py
bob/db/swan/__init__.py
bob/db/swan/common.py
bob/db/swan/config_annotate.py
bob/db/swan/config_audio.py
bob/db/swan/config_pad_audio.py
bob/db/swan/config_pad_video.py
bob/db/swan/config_protocol_grandtest0_voice_bio.py
bob/db/swan/config_protocol_grandtest1_face_spoof.py
bob/db/swan/config_protocol_grandtest1_voice_licit.py
bob/db/swan/config_protocol_licit_p1_face_f1.py
bob/db/swan/config_protocol_licit_p1_face_f2.py
bob/db/swan/config_protocol_licit_p1_face_f3.py
bob/db/swan/config_protocol_licit_p1_face_f4.py
bob/db/swan/config_protocol_licit_p1_face_f5.py
bob/db/swan/config_protocol_licit_p2_face_f1.py
bob/db/swan/config_protocol_licit_p2_face_f2.py
bob/db/swan/config_protocol_licit_p2_face_f3.py
bob/db/swan/config_protocol_licit_p2_face_f4.py
bob/db/swan/config_protocol_licit_p2_face_f5.py
bob/db/swan/config_protocol_licit_p3_face_f1.py
bob/db/swan/config_protocol_licit_p3_face_f2.py
bob/db/swan/config_protocol_licit_p3_face_f3.py
bob/db/swan/config_protocol_licit_p3_face_f4.py
bob/db/swan/config_protocol_licit_p3_face_f5.py
bob/db/swan/config_protocol_pad_p2_face_f1.py
bob/db/swan/config_protocol_pad_p2_face_f2.py
bob/db/swan/config_protocol_pad_p2_face_f3.py
bob/db/swan/config_protocol_pad_p2_face_f4.py
bob/db/swan/config_protocol_pad_p2_face_f5.py
bob/db/swan/config_protocol_paf.py
bob/db/swan/config_protocol_paf1_0.py
bob/db/swan/config_protocol_paf5_0.py
bob/db/swan/config_protocol_paf6_0.py
bob/db/swan/config_protocol_pav4_0.py
bob/db/swan/config_protocol_pav7_0.py
bob/db/swan/config_protocol_spoof_p3_face_f1.py
bob/db/swan/config_protocol_spoof_p3_face_f2.py
bob/db/swan/config_protocol_spoof_p3_face_f3.py
bob/db/swan/config_protocol_spoof_p3_face_f4.py
bob/db/swan/config_protocol_spoof_p3_face_f5.py
bob/db/swan/config_video.py
bob/db/swan/create.py
bob/db/swan/driver.py
bob/db/swan/query_bio.py
bob/db/swan/query_pad.py
