Metadata-Version: 1.1
Name: bob.db.swan
Version: 0.0.4
Summary: SWAN Database Access API for Bob
Home-page: https://gitlab.idiap.ch/bob/bob.db.swan
Author: Amir Mohammadi
Author-email: amir.mohammadi@idiap.ch
License: BSD
Keywords: bob
Platform: UNKNOWN
Classifier: Framework :: Bob
Classifier: Development Status :: 3 - Alpha
Classifier: Intended Audience :: Developers
Classifier: License :: OSI Approved :: BSD License
Classifier: Natural Language :: English
Classifier: Programming Language :: Python
Classifier: Topic :: Scientific/Engineering :: Artificial Intelligence
